apimaticapi/__init__.py
apimaticapi/api_helper.py
apimaticapi/apimaticapi_client.py
apimaticapi/configuration.py
apimaticapi/controllers/__init__.py
apimaticapi/controllers/api_validation_external_apis_controller.py
apimaticapi/controllers/api_validation_imported_apis_controller.py
apimaticapi/controllers/apis_management_controller.py
apimaticapi/controllers/base_controller.py
apimaticapi/controllers/code_generation_external_apis_controller.py
apimaticapi/controllers/code_generation_imported_apis_controller.py
apimaticapi/controllers/docs_portal_management_controller.py
apimaticapi/controllers/transformation_controller.py
apimaticapi/exceptions/__init__.py
apimaticapi/exceptions/api_exception.py
apimaticapi/http/__init__.py
apimaticapi/http/http_call_back.py
apimaticapi/http/http_method_enum.py
apimaticapi/http/http_request.py
apimaticapi/http/http_response.py
apimaticapi/http/auth/__init__.py
apimaticapi/http/auth/custom_header_authentication.py
apimaticapi/models/__init__.py
apimaticapi/models/api_entity.py
apimaticapi/models/api_entity_code_generation.py
apimaticapi/models/api_entity_identifier.py
apimaticapi/models/api_validation_summary.py
apimaticapi/models/attributes.py
apimaticapi/models/auth_scope.py
apimaticapi/models/authentication.py
apimaticapi/models/code_gen_settings.py
apimaticapi/models/code_generation.py
apimaticapi/models/docs_validation_summary.py
apimaticapi/models/endpoints_group.py
apimaticapi/models/environment.py
apimaticapi/models/export_formats.py
apimaticapi/models/field.py
apimaticapi/models/generate_on_prem_portal_via_build_input_request_body.py
apimaticapi/models/generate_sdk_via_file_request_body.py
apimaticapi/models/generate_sdk_via_url_request.py
apimaticapi/models/import_api_version_via_url_request.py
apimaticapi/models/import_api_via_file_request_body.py
apimaticapi/models/import_api_via_url_request.py
apimaticapi/models/import_new_api_version_via_file_request_body.py
apimaticapi/models/import_validation_summary.py
sdksio_apimatic_sdk-3.0.0.dist-info/LICENSE
sdksio_apimatic_sdk-3.0.0.dist-info/METADATA
sdksio_apimatic_sdk-3.0.0.dist-info/WHEEL
sdksio_apimatic_sdk-3.0.0.dist-info/top_level.txt
sdksio_apimatic_sdk-3.0.0.dist-info/RECORD
