Metadata-Version: 2.1
Name: sdksio-apimatic-sdk
Version: 3.0.0
Summary: Use APIMatic API to generate SDKs in Python, Typescript, PHP, Ruby, and GO. You can generate On-Prem portal and many more.
Keywords: APIMatic,SDK,API
Requires-Python: >=3.7
License-File: LICENSE
Requires-Dist: apimatic-core ~=0.2.0
Requires-Dist: apimatic-core-interfaces ~=0.1.0
Requires-Dist: apimatic-requests-client-adapter ~=0.1.0
Requires-Dist: enum34 >=1.1.10,~=1.1
Provides-Extra: testutils
Requires-Dist: pytest >=7.2.2 ; extra == 'testutils'
